distex/__init__.py
distex/pool.py
distex/poolmap.py
distex/processor.py
distex/serializer.py
distex/server.py
distex/slotpool.py
distex/util.py
distex/version.py
distex/worker.py
distex-0.7.2.dist-info/LICENSE
distex-0.7.2.dist-info/METADATA
distex-0.7.2.dist-info/WHEEL
distex-0.7.2.dist-info/entry_points.txt
distex-0.7.2.dist-info/top_level.txt
distex-0.7.2.dist-info/RECORD
