Metadata-Version: 2.1
Name: distex
Version: 0.7.2
Summary: Async distributed process pool using asyncio
Home-page: https://github.com/erdewit/distex
Author: Ewald R. de Wit
Author-email: ewald.de.wit@gmail.com
License: BSD
Keywords: python asyncio parallel distributed computing process pool task queue
Classifier: Development Status :: 4 - Beta
Classifier: Intended Audience :: Science/Research
Classifier: Intended Audience :: Developers
Classifier: License :: OSI Approved :: BSD License
Classifier: Programming Language :: Python :: 3.6
Classifier: Programming Language :: Python :: 3.7
Classifier: Programming Language :: Python :: 3.8
Classifier: Programming Language :: Python :: 3.9
Classifier: Programming Language :: Python :: 3.10
Classifier: Programming Language :: Python :: 3.11
Classifier: Programming Language :: Python :: 3 :: Only
License-File: LICENSE
Requires-Dist: dill
Requires-Dist: cloudpickle
Requires-Dist: eventkit
